motion_correction/__init__.py
motion_correction/algorithms.py
motion_correction/cudipy/LICENSE
motion_correction/cudipy/__init__.py
motion_correction/cudipy/_utils.py
motion_correction/cudipy/_vendored/__init__.py
motion_correction/cudipy/_vendored/_cupy/LICENSE
motion_correction/cudipy/_vendored/_cupy/__init__.py
motion_correction/cudipy/_vendored/_cupy/_filters_core.py
motion_correction/cudipy/_vendored/_cupy/_interp_kernels.py
motion_correction/cudipy/_vendored/_cupy/_util.py
motion_correction/cudipy/align/__init__.py
motion_correction/cudipy/align/crosscorr.py
motion_correction/cudipy/align/imaffine.py
motion_correction/cudipy/align/imwarp.py
motion_correction/cudipy/align/metrics.py
motion_correction/cudipy/align/scalespace.py
motion_correction/cudipy/align/vector_fields.py
motion_correction/cudipy/denoise/__init__.py
motion_correction/cudipy/denoise/gibbs.py
motion_correction/cudipy/denoise/noise_estimate.py
motion_correction/cudipy/denoise/pca_noise_estimate.py
motion_correction/cudipy/info.py
motion_correction/cudipy/segment/__init__.py
motion_correction/cudipy/segment/_icm_kernels.py
motion_correction/cudipy/segment/mask.py
motion_correction/cudipy/segment/mrf.py
motion_correction/cudipy/segment/tests/test_mask.py.bak
motion_correction/cudipy/segment/tissue.py
motion_correction/cudipy/sims/__init__.py
motion_correction/cudipy/sims/voxel.py
motion_correction/cudipy/viz/__init__.py
motion_correction/cudipy/viz/regtools.py
motion_correction/desktop/__init__.py
motion_correction/desktop/flim_aligner.py
motion_correction/desktop/utility.py
motion_correction/image_registration/.DS_Store
motion_correction/image_registration/FITS_tools/__init__.py
motion_correction/image_registration/FITS_tools/fits_overlap.py
motion_correction/image_registration/FITS_tools/hcongrid.py
motion_correction/image_registration/FITS_tools/load_header.py
motion_correction/image_registration/FITS_tools/match_images.py
motion_correction/image_registration/LICENSE
motion_correction-0.2.2.dist-info/AUTHORS.rst
motion_correction-0.2.2.dist-info/LICENSE
motion_correction-0.2.2.dist-info/METADATA
motion_correction-0.2.2.dist-info/WHEEL
motion_correction-0.2.2.dist-info/RECORD
